pgl/__init__.py
pgl/bigraph.py
pgl/dataset.py
pgl/graph.py
pgl/graph_kernel.cpython-310-x86_64-linux-gnu.so
pgl/graph_kernel.pyx
pgl/heter_graph.py
pgl/math.py
pgl/message.py
pgl/partition.py
pgl/data/BlogCatalog/edges.csv
pgl/data/BlogCatalog/group-edges.csv
pgl/data/BlogCatalog/groups.csv
pgl/data/BlogCatalog/nodes.csv
pgl/data/arXiv/ca-AstroPh.txt
pgl/data/citeseer/ind.citeseer.allx
pgl/data/citeseer/ind.citeseer.ally
pgl/data/citeseer/ind.citeseer.graph
pgl/data/citeseer/ind.citeseer.test.index
pgl/data/citeseer/ind.citeseer.tx
pgl/data/citeseer/ind.citeseer.ty
pgl/data/citeseer/ind.citeseer.x
pgl/data/citeseer/ind.citeseer.y
pgl/data/cora/README
pgl/data/cora/cora.cites
pgl/data/cora/cora.content
pgl/data/pubmed/ind.pubmed.allx
pgl/data/pubmed/ind.pubmed.ally
pgl/data/pubmed/ind.pubmed.graph
pgl/data/pubmed/ind.pubmed.test.index
pgl/data/pubmed/ind.pubmed.tx
pgl/data/pubmed/ind.pubmed.ty
pgl/data/pubmed/ind.pubmed.x
pgl/data/pubmed/ind.pubmed.y
pgl/distributed/__init__.py
pgl/distributed/dist_graph.py
pgl/distributed/helper.py
pgl/distributed/launch.py
pgl/nn/__init__.py
pgl/nn/conv.py
pgl/nn/gmt_pool.py
pgl/nn/pool.py
pgl/nn/functional/__init__.py
pgl/nn/functional/graph_op.py
pgl/sampling/__init__.py
pgl/sampling/custom.py
pgl/sampling/sage.py
pgl/sampling/walk.py
pgl/third_party/metis/BUILD-Windows.txt
pgl/third_party/metis/BUILD.txt
pgl/third_party/metis/CMakeLists.txt
pgl/third_party/metis/Changelog
pgl/third_party/metis/Install.txt
pgl/third_party/metis/LICENSE.txt
pgl/third_party/metis/Makefile
pgl/third_party/metis/vsgen.bat
pgl/third_party/metis/GKlib/BUILD.txt
pgl/third_party/metis/GKlib/CMakeLists.txt
pgl/third_party/metis/GKlib/GKlib.h
pgl/third_party/metis/GKlib/GKlibSystem.cmake
pgl/third_party/metis/GKlib/Makefile
pgl/third_party/metis/GKlib/b64.c
pgl/third_party/metis/GKlib/blas.c
pgl/third_party/metis/GKlib/csr.c
pgl/third_party/metis/GKlib/error.c
pgl/third_party/metis/GKlib/evaluate.c
pgl/third_party/metis/GKlib/fkvkselect.c
pgl-2.2.6.dist-info/LICENSE
pgl-2.2.6.dist-info/METADATA
pgl-2.2.6.dist-info/WHEEL
pgl-2.2.6.dist-info/top_level.txt
pgl-2.2.6.dist-info/RECORD
